seiwhale/cli.py
seiwhale-0.0.1.dist-info/entry_points.txt
seiwhale-0.0.1.dist-info/WHEEL
seiwhale-0.0.1.dist-info/METADATA
seiwhale-0.0.1.dist-info/RECORD
