Metadata-Version: 2.1
Name: seiwhale
Version: 0.0.1
Summary: Rapid Dockerfile generator
License: MIT
Author: Naruhide KITADA
Author-email: kitfactory@gmail.com
Requires-Python: >=3.7,<4.0
Classifier: License :: OSI Approved :: MIT License
Classifier: Programming Language :: Python :: 3
Classifier: Programming Language :: Python :: 3.7
Classifier: Programming Language :: Python :: 3.8
